{
  "type": "Feature",
  "id": "06030340:MT:USGS",
  "geometry": {
    "type": "Point",
    "coordinates": [
      -111.966657439858,
      45.7333234600951
    ]
  },
  "properties": {
    "name": "South Boulder R nr Harrison",
    "source": "ref"
  }
}
