{
  "type": "Feature",
  "id": "06040300:MT:USGS",
  "geometry": {
    "type": "Point",
    "coordinates": [
      -111.583317594539,
      45.3499934608613
    ]
  },
  "properties": {
    "name": "Jack Ck nr Ennis",
    "source": "ref"
  }
}
