{
  "type": "Feature",
  "id": "06289820:WY:USGS",
  "geometry": {
    "type": "Point",
    "coordinates": [
      -107.41665858074,
      44.9833231225031
    ]
  },
  "properties": {
    "name": "East Pass Ck nr Dayton",
    "source": "ref"
  }
}
