{
  "type": "Feature",
  "id": "06295250:MT:USGS",
  "geometry": {
    "type": "Point",
    "coordinates": [
      -106.566658640169,
      45.7666629621373
    ]
  },
  "properties": {
    "name": "Rosebud Ck nr Colstrip",
    "source": "ref"
  }
}
