{
  "type": "Feature",
  "id": "06301500:WY:USGS",
  "geometry": {
    "type": "Point",
    "coordinates": [
      -107.299988670457,
      44.6166631527015
    ]
  },
  "properties": {
    "name": "WF Big Goose Ck nr Big Horn",
    "source": "ref"
  }
}
