{
  "type": "Feature",
  "id": "06307500:MT:USGS",
  "geometry": {
    "type": "Point",
    "coordinates": [
      -106.766658704778,
      45.1333230489103
    ]
  },
  "properties": {
    "name": "Tongue R at Dam nr Decker",
    "source": "ref"
  }
}
