{"type" : "Feature", "id" : "06311060:WY:USGS", "geometry" : {"type":"Point","coordinates":[-107.016658838031,43.9999931988841]}, "properties" : {"name" : "NF Powder R blw Bull Ck nr Hazelton", "source" : "ref"}}
