{"type" : "Feature", "id" : "06428500:SD:USGS", "geometry" : {"type":"Point","coordinates":[-104.049989419168,44.7499928625367]}, "properties" : {"name" : "Belle Fourche R at Wy-Sd State Line", "source" : "ref"}}
