{"type" : "Feature", "id" : "06425720:WY:USGS", "geometry" : {"type":"Point","coordinates":[-105.38331922067,43.983323064858]}, "properties" : {"name" : "Belle Fourche R blw Rattlesnake Ck", "source" : "ref"}}
