{
  "type": "Feature",
  "id": "07095000:CO:USGS",
  "geometry": {
    "type": "Point",
    "coordinates": [
      -105.483599949609,
      38.1861038314517
    ]
  },
  "properties": {
    "name": "Grape Ck nr Westcliffe",
    "source": "ref"
  }
}
