{"type" : "Feature", "id" : "09010000:CO:USGS", "geometry" : {"type":"Point","coordinates":[-105.821589611757,40.4775935402546]}, "properties" : {"name" : "Grand River Ditch at La Poudre Pass", "source" : "ref"}}
