{
  "type": "Feature",
  "id": "09282399:UT:USGS",
  "geometry": {
    "type": "Point",
    "coordinates": [
      -111.108558497023,
      40.2108639654195
    ]
  },
  "properties": {
    "name": "Strawberry Aqueduct",
    "source": "ref"
  }
}
