{"type" : "Feature", "id" : "09449000:AZ:USGS", "geometry" : {"type":"Point","coordinates":[-110.216659370648,33.1833248245154]}, "properties" : {"name" : "Diversions From Gila R In Safford Valley", "source" : "ref"}}
