{
  "type": "Feature",
  "id": "09471000:AZ:USGS",
  "geometry": {
    "type": "Point",
    "coordinates": [
      -110.166659483085,
      31.6333250497818
    ]
  },
  "properties": {
    "name": "San Pedro R at Charleston",
    "source": "ref"
  }
}
