{
  "type": "Feature",
  "id": "10156000:UT:USGS",
  "geometry": {
    "type": "Point",
    "coordinates": [
      -111.466378387005,
      40.4852739609502
    ]
  },
  "properties": {
    "name": "Snake Ck nr Charleston",
    "source": "ref"
  }
}
