{
  "type": "Feature",
  "id": "10155400:UT:USGS",
  "geometry": {
    "type": "Point",
    "coordinates": [
      -111.433318392111,
      40.4999939571525
    ]
  },
  "properties": {
    "name": "Spring Ck nr Heber City",
    "source": "ref"
  }
}
