{"type" : "Feature", "id" : "1132000N:CA:USGS", "geometry" : {"type":"Point","coordinates":[-120.849986969709,38.2499949003697]}, "properties" : {"name" : "Pardee Reservoir Near Valley Springs, CA", "source" : "ref"}}
