{"type" : "Feature", "id" : "11342000:CA:USGS", "geometry" : {"type":"Point","coordinates":[-122.417226367443,40.9395848099049]}, "properties" : {"name" : "Sacramento R A Delta CA", "source" : "ref"}}
