{
  "type": "Feature",
  "id": "11365000:CA:USGS",
  "geometry": {
    "type": "Point",
    "coordinates": [
      -122.017206443867,
      40.843204783206
    ]
  },
  "properties": {
    "name": "Pit R nr Montgomery Creek CA",
    "source": "ref"
  }
}
