{"type" : "Feature", "id" : "11392500:CA:USGS", "geometry" : {"type":"Point","coordinates":[-120.583316821909,39.7499947514157]}, "properties" : {"name" : "Mf Feather R nr Clio, CA", "source" : "ref"}}
