{"type" : "Feature", "id" : "12NK1200:BC:USGS", "geometry" : {"type":"Point","coordinates":[-115.049986011624,49.2999934826651]}, "properties" : {"name" : "Elk R at Stanley Park, BC", "source" : "ref"}}
