{"type" : "Feature", "id" : "13055002:ID:USGS", "geometry" : {"type":"Point","coordinates":[-111.583317851628,43.8999936031068]}, "properties" : {"name" : "Sum Of Major Divs Ashton To St Anthony", "source" : "ref"}}
