{"type" : "Feature", "id" : "13069000:ID:USGS", "geometry" : {"type":"Point","coordinates":[-112.333317791079,43.3333237263391]}, "properties" : {"name" : "Div Fm Snake R Bet Shelly And Blackfoot", "source" : "ref"}}
