{"type" : "Feature", "id" : "13078205:ID:USGS", "geometry" : {"type":"Point","coordinates":[-113.433317768587,42.0666639487837]}, "properties" : {"name" : "Raft River Below Onemile Cr, nr Malta, I", "source" : "ref"}}
