{"type" : "Feature", "id" : "14015000:WA:USGS", "geometry" : {"type":"Point","coordinates":[-118.266656142795,46.0666640501283]}, "properties" : {"name" : "Mill Ck at Walla Walla", "source" : "ref"}}
