{"type" : "Feature", "id" : "15239900:AK:USGS", "geometry" : {"type":"Point","coordinates":[-151.753037962819,59.7472185626085]}, "properties" : {"name" : "Anchor R nr Anchor Point AK", "source" : "ref"}}
