{"type" : "Feature", "id" : "15292700:AK:USGS", "geometry" : {"type":"Point","coordinates":[-150.019176126342,62.3464384562467]}, "properties" : {"name" : "Talkeetna R nr Talkeetna", "source" : "ref"}}
