{
  "type": "Feature",
  "id": "15356000:AK:USGS",
  "geometry": {
    "type": "Point",
    "coordinates": [
      -141.200064235715,
      64.7891670965985
    ]
  },
  "properties": {
    "name": "Yukon R at Eagle",
    "source": "ref"
  }
}
