{"type" : "Feature", "id" : "159AE001:YK:USGS", "geometry" : {"type":"Point","coordinates":[-133.299978334354,60.4833256518659]}, "properties" : {"name" : "Teslin River Near Teslin", "source" : "ref"}}
