{"type" : "Feature", "id" : "9355200:NM:USGS", "geometry" : {"type":"Point","coordinates":[-107.61372961443,36.8057141622453]}, "properties" : {"name" : "Navajo Indian Irrigation Proj Diversion", "source" : "ref"}}
