{
  "type": "Feature",
  "id": "MKZO:OR:USGS",
  "geometry": {
    "type": "Point",
    "coordinates": [
      -122.466645828184,
      44.1166545984018
    ]
  },
  "properties": {
    "name": "Mckenzie River Near Vida",
    "source": "ref"
  }
}
