{
  "type": "Feature",
  "id": "06078500:MT:USGS",
  "geometry": {
    "type": "Point",
    "coordinates": [
      -112.85931685801,
      47.6398533802285
    ]
  },
  "properties": {
    "name": "NF Sun R nr Augusta",
    "source": "ref",
    "begindate": "5/1/1911",
    "countyname": "Teton",
    "enddate": "2100-01-01T08:00:00Z",
    "active": true,
    "huc": 100301040111,
    "winter_start_month": 11,
    "winter_end_month": 3,
    "nwccname": "NF Sun R nr Augusta",
    "elevation": "4786",
    "basinarea": 259.0,
    "awdb_id": "06078500",
    "usgs_id": "6078500",
    "usgsname": "North Fork Sun River near Augusta MT",
    "forecastpoint": false,
    "bagis_aoiname": null,
    "aoi_exist": null
  }
}
