{
  "type": "Feature",
  "id": "06131000:MT:USGS",
  "geometry": {
    "type": "Point",
    "coordinates": [
      -106.349988389338,
      47.3499927744667
    ]
  },
  "properties": {
    "name": "Big Dry Ck nr Van Norman Valier",
    "source": "ref"
  }
}
