{
  "type": "Feature",
  "id": "06223500:WY:USGS",
  "geometry": {
    "type": "Point",
    "coordinates": [
      -109.183318465645,
      43.2833234617656
    ]
  },
  "properties": {
    "name": "Willow Creek Near Crowheart",
    "source": "ref",
    "begindate": "10/1/1921",
    "countyname": "Fremont",
    "enddate": "2007-06-01T07:00:00Z",
    "active": false,
    "huc": 100800010707,
    "winter_start_month": 11,
    "winter_end_month": 3,
    "nwccname": "Willow Creek Near Crowheart",
    "elevation": "6080",
    "basinarea": 55.4,
    "awdb_id": "06223500",
    "usgs_id": "6223500",
    "usgsname": "WILLOW CREEK NEAR CROWHEART, WY",
    "forecastpoint": false,
    "bagis_aoiname": null,
    "aoi_exist": null
  }
}
