{
  "type": "Feature",
  "id": "06291000:MT:USGS",
  "geometry": {
    "type": "Point",
    "coordinates": [
      -107.29998855809,
      45.2666630817683
    ]
  },
  "properties": {
    "name": "Owl Ck nr Lodge Grass",
    "source": "ref",
    "begindate": "1/1/1939",
    "countyname": "Big Horn",
    "enddate": "1992-10-01T07:00:00Z",
    "active": false,
    "huc": 100800160105,
    "winter_start_month": 11,
    "winter_end_month": 3,
    "nwccname": "Owl Ck nr Lodge Grass",
    "elevation": "3460",
    "basinarea": 163.0,
    "awdb_id": "06291000",
    "usgs_id": "6291000",
    "usgsname": "Owl Creek near Lodge Grass MT",
    "forecastpoint": false,
    "bagis_aoiname": null,
    "aoi_exist": null
  }
}
