{
  "type": "Feature",
  "id": "06670500:WY:USGS",
  "geometry": {
    "type": "Point",
    "coordinates": [
      -104.53331968648,
      42.199993218889
    ]
  },
  "properties": {
    "name": "Laramie R nr Ft Laramie",
    "source": "ref",
    "begindate": "1/1/1915",
    "countyname": "Goshen",
    "enddate": "2100-01-01T08:00:00Z",
    "active": true,
    "huc": 101800110906,
    "winter_start_month": 11,
    "winter_end_month": 3,
    "nwccname": "Laramie R nr Ft Laramie",
    "elevation": "4220",
    "basinarea": 4564.0,
    "awdb_id": "06670500",
    "usgs_id": "6670500",
    "usgsname": "LARAMIE RIVER NEAR FORT LARAMIE, WY",
    "forecastpoint": false,
    "bagis_aoiname": null,
    "aoi_exist": null
  }
}
