{
  "type": "Feature",
  "id": "07081899:CO:USGS",
  "geometry": {
    "type": "Point",
    "coordinates": [
      -106.4321896163,
      39.281093743725
    ]
  },
  "properties": {
    "name": "Homestake Tunnel",
    "source": "ref",
    "begindate": "10/1/1966",
    "countyname": "Lake",
    "enddate": "2100-01-01T08:00:00Z",
    "active": true,
    "huc": 110200010203,
    "winter_start_month": 11,
    "winter_end_month": 3,
    "nwccname": "Homestake Tunnel",
    "elevation": "10091",
    "basinarea": null,
    "awdb_id": "07081899",
    "usgs_id": "7081899",
    "usgsname": null,
    "forecastpoint": false,
    "bagis_aoiname": null,
    "aoi_exist": null
  }
}
