{
  "type": "Feature",
  "id": "08290000:NM:USGS",
  "geometry": {
    "type": "Point",
    "coordinates": [
      -106.111680012511,
      36.0735541769972
    ]
  },
  "properties": {
    "name": "Rio Chama nr Chamita",
    "source": "ref"
  }
}
