{
  "type": "Feature",
  "id": "09040000:CO:USGS",
  "geometry": {
    "type": "Point",
    "coordinates": [
      -106.283319546288,
      40.1499936164766
    ]
  },
  "properties": {
    "name": "East Fork Troublesome Ck nr Troublesome",
    "source": "ref"
  }
}
