{
  "type": "Feature",
  "id": "09237500:CO:USGS",
  "geometry": {
    "type": "Point",
    "coordinates": [
      -106.830819406484,
      40.285273638306
    ]
  },
  "properties": {
    "name": "Yampa R nr Oak Creek",
    "source": "ref"
  }
}
