{
  "type": "Feature",
  "id": "09313000:UT:USGS",
  "geometry": {
    "type": "Point",
    "coordinates": [
      -110.849988611757,
      39.7166640040899
    ]
  },
  "properties": {
    "name": "Price R nr Heiner, UT",
    "source": "ref",
    "begindate": "6/1/1934",
    "countyname": "Carbon",
    "enddate": "2014-04-01T07:00:00Z",
    "active": false,
    "huc": 140600070506,
    "winter_start_month": 11,
    "winter_end_month": 3,
    "nwccname": "Price R nr Heiner, UT",
    "elevation": "6000",
    "basinarea": 455.0,
    "awdb_id": "09313000",
    "usgs_id": "9313000",
    "usgsname": "PRICE RIVER NEAR HEINER, UTAH",
    "forecastpoint": false,
    "bagis_aoiname": null,
    "aoi_exist": null
  }
}
