{
  "type": "Feature",
  "id": "10155400:UT:USGS",
  "geometry": {
    "type": "Point",
    "coordinates": [
      -111.433318392111,
      40.4999939571525
    ]
  },
  "properties": {
    "name": "Spring Ck nr Heber City",
    "source": "ref",
    "begindate": "5/1/1993",
    "countyname": "Wasatch",
    "enddate": "2005-04-01T08:00:00Z",
    "active": false,
    "huc": 160202030303,
    "winter_start_month": 11,
    "winter_end_month": 3,
    "nwccname": "Spring Ck nr Heber City",
    "elevation": "5500",
    "basinarea": 60.8,
    "awdb_id": "10155400",
    "usgs_id": "10155400",
    "usgsname": "SPRING CREEK NEAR HEBER CITY, UT",
    "forecastpoint": false,
    "bagis_aoiname": null,
    "aoi_exist": null
  }
}
