{
  "type": "Feature",
  "id": "10185000:UT:USGS",
  "geometry": {
    "type": "Point",
    "coordinates": [
      -111.866658595266,
      38.0999942704035
    ]
  },
  "properties": {
    "name": "Antimony Ck nr Antimony, UT",
    "source": "ref",
    "begindate": "10/1/1946",
    "countyname": "Garfield",
    "enddate": "1976-10-01T07:00:00Z",
    "active": false,
    "huc": 160300020503,
    "winter_start_month": 11,
    "winter_end_month": 3,
    "nwccname": "Antimony Ck nr Antimony, UT",
    "elevation": "7000",
    "basinarea": 50.3,
    "awdb_id": "10185000",
    "usgs_id": "10185000",
    "usgsname": "ANTIMONY CREEK NEAR ANTIMONY, UTAH",
    "forecastpoint": false,
    "bagis_aoiname": null,
    "aoi_exist": null
  }
}
