{
  "type": "Feature",
  "id": "10185000:UT:USGS",
  "geometry": {
    "type": "Point",
    "coordinates": [
      -111.866658595266,
      38.0999942704035
    ]
  },
  "properties": {
    "name": "Antimony Ck nr Antimony, UT",
    "source": "ref"
  }
}
