{
  "type": "Feature",
  "id": "10239000:UT:USGS",
  "geometry": {
    "type": "Point",
    "coordinates": [
      -112.83331839094,
      38.216654323725
    ]
  },
  "properties": {
    "name": "Beaver River at Rocky Ford Dam, nr Miner",
    "source": "ref"
  }
}
