{
  "type": "Feature",
  "id": "10236575:UT:USGS",
  "geometry": {
    "type": "Point",
    "coordinates": [
      -112.559458430272,
      38.3443142895234
    ]
  },
  "properties": {
    "name": "North Creek nr Beaver",
    "source": "ref"
  }
}
