{
  "type": "Feature",
  "id": "1140470N:CA:USGS",
  "geometry": {
    "type": "Point",
    "coordinates": [
      -121.449986680529,
      39.7833248179858
    ]
  },
  "properties": {
    "name": "NF Feather R nr Big Bar NWS",
    "source": "ref",
    "begindate": "1/1/2004",
    "countyname": "Butte",
    "enddate": "2100-01-01T08:00:00Z",
    "active": true,
    "huc": 180201210803,
    "winter_start_month": 11,
    "winter_end_month": 3,
    "nwccname": "NF Feather R nr Big Bar NWS",
    "elevation": "1306",
    "basinarea": null,
    "awdb_id": "1140470N",
    "usgs_id": "1140470N",
    "usgsname": null,
    "forecastpoint": false,
    "bagis_aoiname": null,
    "aoi_exist": null
  }
}
