{
  "type": "Feature",
  "id": "1141300N:CA:USGS",
  "geometry": {
    "type": "Point",
    "coordinates": [
      -120.933316797455,
      39.5166547983691
    ]
  },
  "properties": {
    "name": "N Yuba R bl Goodyears Bar Ca (NWS)",
    "source": "ref",
    "begindate": "10/31/1930",
    "countyname": "Sierra",
    "enddate": "2100-01-01T08:00:00Z",
    "active": true,
    "huc": 180201250302,
    "winter_start_month": 11,
    "winter_end_month": 3,
    "nwccname": "N Yuba R bl Goodyears Bar Ca (NWS)",
    "elevation": "2453",
    "basinarea": null,
    "awdb_id": "1141300N",
    "usgs_id": "1141300N",
    "usgsname": null,
    "forecastpoint": true,
    "bagis_aoiname": null,
    "aoi_exist": false
  }
}
