{
  "type": "Feature",
  "id": "11441900:CA:USGS",
  "geometry": {
    "type": "Point",
    "coordinates": [
      -120.539356948697,
      38.8237848264991
    ]
  },
  "properties": {
    "name": "Silver C bl Camino Div Dam CA",
    "source": "ref"
  }
}
