{
  "type": "Feature",
  "id": "12331900:MT:USGS",
  "geometry": {
    "type": "Point",
    "coordinates": [
      -113.583316906837,
      46.71666352951
    ]
  },
  "properties": {
    "name": "Clark Fk nr Clinton",
    "source": "ref"
  }
}
