{
  "type": "Feature",
  "id": "12353280:MT:USGS",
  "geometry": {
    "type": "Point",
    "coordinates": [
      -114.416656663351,
      47.0666635839811
    ]
  },
  "properties": {
    "name": "Ninemile Ck nr Huson",
    "source": "ref",
    "begindate": "1/1/1973",
    "countyname": "Missoula",
    "enddate": "1990-10-01T07:00:00Z",
    "active": false,
    "huc": 170102040305,
    "winter_start_month": 11,
    "winter_end_month": 3,
    "nwccname": "Ninemile Ck nr Huson",
    "elevation": "3028",
    "basinarea": 170.0,
    "awdb_id": "12353280",
    "usgs_id": "12353280",
    "usgsname": "Ninemile Creek near Huson MT",
    "forecastpoint": false,
    "bagis_aoiname": null,
    "aoi_exist": null
  }
}
