{
  "type": "Feature",
  "id": "12365000:MT:USGS",
  "geometry": {
    "type": "Point",
    "coordinates": [
      -114.383316387873,
      48.3166634836294
    ]
  },
  "properties": {
    "name": "Stillwater R nr Whitefish",
    "source": "ref",
    "begindate": "10/1/1930",
    "countyname": "Flathead",
    "enddate": "2006-10-01T07:00:00Z",
    "active": false,
    "huc": 170102100403,
    "winter_start_month": 11,
    "winter_end_month": 3,
    "nwccname": "Stillwater R nr Whitefish",
    "elevation": "2953",
    "basinarea": 558.0,
    "awdb_id": "12365000",
    "usgs_id": "12365000",
    "usgsname": "Stillwater River near Whitefish MT",
    "forecastpoint": false,
    "bagis_aoiname": null,
    "aoi_exist": null
  }
}
