{
  "type": "Feature",
  "id": "12391000:MT:USGS",
  "geometry": {
    "type": "Point",
    "coordinates": [
      -115.349986359545,
      47.599993637833
    ]
  },
  "properties": {
    "name": "Clark Fk at Thompson Falls",
    "source": "ref"
  }
}
