{
  "type": "Feature",
  "id": "12442000:WA:USGS",
  "geometry": {
    "type": "Point",
    "coordinates": [
      -119.699985245886,
      48.8333240242495
    ]
  },
  "properties": {
    "name": "Toats Coulee Creek nr Loomis, WA",
    "source": "ref"
  }
}
