{
  "type": "Feature",
  "id": "12446500:WA:USGS",
  "geometry": {
    "type": "Point",
    "coordinates": [
      -119.733315316602,
      48.5333240458019
    ]
  },
  "properties": {
    "name": "Salmon Creek nr Conconully WA",
    "source": "ref",
    "begindate": "10/1/1911",
    "countyname": "Okanogan",
    "enddate": "1994-01-01T08:00:00Z",
    "active": false,
    "huc": 170200062104,
    "winter_start_month": 11,
    "winter_end_month": 3,
    "nwccname": "Salmon Creek nr Conconully WA",
    "elevation": "2200",
    "basinarea": 121.0,
    "awdb_id": "12446500",
    "usgs_id": "12446500",
    "usgsname": "SALMON CREEK NEAR CONCONULLY, WA",
    "forecastpoint": false,
    "bagis_aoiname": null,
    "aoi_exist": null
  }
}
