{
  "type": "Feature",
  "id": "13054999:ID:USGS",
  "geometry": {
    "type": "Point",
    "coordinates": [
      -111.364987892538,
      43.9272135816409
    ]
  },
  "properties": {
    "name": "Sum Pump Divs Teton Rivs Leigh Ck-St A",
    "source": "ref",
    "begindate": "10/1/1974",
    "countyname": "Teton",
    "enddate": "2100-01-01T08:00:00Z",
    "active": true,
    "huc": 170402040501,
    "winter_start_month": 11,
    "winter_end_month": 3,
    "nwccname": "Sum Pump Divs Teton Rivs Leigh Ck-St A",
    "elevation": "5000",
    "basinarea": null,
    "awdb_id": "13054999",
    "usgs_id": "13054999",
    "usgsname": null,
    "forecastpoint": false,
    "bagis_aoiname": null,
    "aoi_exist": null
  }
}
