{
  "type": "Feature",
  "id": "13054999:ID:USGS",
  "geometry": {
    "type": "Point",
    "coordinates": [
      -111.364987892538,
      43.9272135816409
    ]
  },
  "properties": {
    "name": "Sum Pump Divs Teton Rivs Leigh Ck-St A",
    "source": "ref"
  }
}
