{
  "type": "Feature",
  "id": "13239000:ID:USGS",
  "geometry": {
    "type": "Point",
    "coordinates": [
      -116.116656769722,
      44.9044939275383
    ]
  },
  "properties": {
    "name": "NF Payette River at Mccall",
    "source": "ref",
    "begindate": "9/1/1908",
    "countyname": "Valley",
    "enddate": "2100-01-01T08:00:00Z",
    "active": true,
    "huc": 170501230204,
    "winter_start_month": 11,
    "winter_end_month": 3,
    "nwccname": "NF Payette River at Mccall",
    "elevation": "4968",
    "basinarea": 144.0,
    "awdb_id": "13239000",
    "usgs_id": "13239000",
    "usgsname": "NF PAYETTE RIVER AT MCCALL ID",
    "forecastpoint": false,
    "bagis_aoiname": null,
    "aoi_exist": null
  }
}
