{
  "type": "Feature",
  "id": "14105700:OR:USGS",
  "geometry": {
    "type": "Point",
    "coordinates": [
      -121.17338573927,
      45.6073343762255
    ]
  },
  "properties": {
    "name": "Columbia R at The Dalles-NWS",
    "source": "ref",
    "begindate": "18780601",
    "countyname": "Wasco",
    "enddate": "2100-01-01T08:00:00Z",
    "active": true,
    "huc": 170701050406,
    "winter_start_month": 11,
    "winter_end_month": 3,
    "nwccname": "Columbia R at The Dalles-NWS",
    "elevation": "120",
    "basinarea": 237000.0,
    "awdb_id": "14105700",
    "usgs_id": "14105700",
    "usgsname": "COLUMBIA RIVER AT THE DALLES, OR",
    "forecastpoint": true,
    "bagis_aoiname": null,
    "aoi_exist": false
  }
}
