{
  "type": "Feature",
  "id": "14400000:OR:USGS",
  "geometry": {
    "type": "Point",
    "coordinates": [
      -124.18331592377,
      42.1166548863006
    ]
  },
  "properties": {
    "name": "Chetco R nr Brookings",
    "source": "ref",
    "begindate": "10/1/1969",
    "countyname": "Curry",
    "enddate": "2100-01-01T08:00:00Z",
    "active": true,
    "huc": 171003120109,
    "winter_start_month": 11,
    "winter_end_month": 3,
    "nwccname": "Chetco R nr Brookings",
    "elevation": "49",
    "basinarea": 271.0,
    "awdb_id": "14400000",
    "usgs_id": "14400000",
    "usgsname": "CHETCO RIVER NEAR BROOKINGS, OR",
    "forecastpoint": false,
    "bagis_aoiname": null,
    "aoi_exist": null
  }
}
