{
  "type": "Feature",
  "id": "15238600:AK:USGS",
  "geometry": {
    "type": "Point",
    "coordinates": [
      -149.4521977197,
      60.0694382172003
    ]
  },
  "properties": {
    "name": "Spruce Ck nr Seward",
    "source": "ref",
    "begindate": "9/1/1967",
    "countyname": "Kenai Peninsula",
    "enddate": "2100-01-01T08:00:00Z",
    "active": true,
    "huc": 190202020511,
    "winter_start_month": 11,
    "winter_end_month": 3,
    "nwccname": "Spruce Ck nr Seward",
    "elevation": "100",
    "basinarea": 9.3,
    "awdb_id": "15238600",
    "usgs_id": "15238600",
    "usgsname": "SPRUCE C NR SEWARD AK",
    "forecastpoint": false,
    "bagis_aoiname": null,
    "aoi_exist": null
  }
}
