{
  "type": "Feature",
  "id": "15896000:AK:USGS",
  "geometry": {
    "type": "Point",
    "coordinates": [
      -148.962757184854,
      70.2813888107712
    ]
  },
  "properties": {
    "name": "Kuparuk R nr Deadhorse",
    "source": "ref",
    "begindate": "1/1/1971",
    "countyname": "North Slope",
    "enddate": "2100-01-01T08:00:00Z",
    "active": true,
    "huc": 190604011306,
    "winter_start_month": 11,
    "winter_end_month": 3,
    "nwccname": "Kuparuk R nr Deadhorse",
    "elevation": "0",
    "basinarea": 3340.0,
    "awdb_id": "15896000",
    "usgs_id": "15896000",
    "usgsname": "KUPARUK R NR DEADHORSE AK",
    "forecastpoint": true,
    "bagis_aoiname": null,
    "aoi_exist": false
  }
}
