{
  "type": "Feature",
  "id": "158AB001:YK:USGS",
  "geometry": {
    "type": "Point",
    "coordinates": [
      -137.966648107946,
      60.1166663818023
    ]
  },
  "properties": {
    "name": "Alsek River abv Bates River",
    "source": "ref"
  }
}
