{
  "type": "Feature",
  "id": "3500570:CO:USGS",
  "geometry": {
    "type": "Point",
    "coordinates": [
      -105.383390048895,
      37.4274139346223
    ]
  },
  "properties": {
    "name": "Sdc-Trinchera Canal",
    "source": "ref",
    "begindate": "1/1/1964",
    "countyname": "Costilla",
    "enddate": "2100-01-01T08:00:00Z",
    "active": true,
    "huc": 130100020505,
    "winter_start_month": 11,
    "winter_end_month": 3,
    "nwccname": "Sdc-Trinchera Canal",
    "elevation": "7975",
    "basinarea": null,
    "awdb_id": "3500570",
    "usgs_id": "3500570",
    "usgsname": null,
    "forecastpoint": false,
    "bagis_aoiname": null,
    "aoi_exist": null
  }
}
