{
  "type": "Feature",
  "id": "CO0048:CO:USGS",
  "geometry": {
    "type": "Point",
    "coordinates": [
      -108.210989428469,
      37.3959941174405
    ]
  },
  "properties": {
    "name": "Weber Reservoir Outlet",
    "source": "ref",
    "begindate": "1/1/1900",
    "countyname": "Montezuma",
    "enddate": "2100-01-01T08:00:00Z",
    "active": true,
    "huc": 140801070101,
    "winter_start_month": 11,
    "winter_end_month": 3,
    "nwccname": "Weber Reservoir Outlet",
    "elevation": "8200",
    "basinarea": null,
    "awdb_id": "CO0048",
    "usgs_id": "CO0048",
    "usgsname": null,
    "forecastpoint": false,
    "bagis_aoiname": null,
    "aoi_exist": null
  }
}
