{
  "type": "Feature",
  "id": "CO0006:CO:USGS",
  "geometry": {
    "type": "Point",
    "coordinates": [
      -106.306089634748,
      39.361093723448
    ]
  },
  "properties": {
    "name": "Ewing Ditch",
    "source": "ref"
  }
}
