{
  "type": "Feature",
  "id": "LOSODVCO:CO:USGS",
  "geometry": {
    "type": "Point",
    "coordinates": [
      -106.81054976467,
      37.0755540735213
    ]
  },
  "properties": {
    "name": "Little Oso Div nr Chromo",
    "source": "ref",
    "begindate": "1/1/1900",
    "countyname": "Archuleta",
    "enddate": "2100-01-01T08:00:00Z",
    "active": true,
    "huc": 140801010604,
    "winter_start_month": 11,
    "winter_end_month": 3,
    "nwccname": "Little Oso Div nr Chromo",
    "elevation": "7775",
    "basinarea": null,
    "awdb_id": "LOSODVCO",
    "usgs_id": "LOSODVCO",
    "usgsname": null,
    "forecastpoint": false,
    "bagis_aoiname": null,
    "aoi_exist": null
  }
}
