{
  "type": "Feature",
  "id": "LOSODVCO:CO:USGS",
  "geometry": {
    "type": "Point",
    "coordinates": [
      -106.81054976467,
      37.0755540735213
    ]
  },
  "properties": {
    "name": "Little Oso Div nr Chromo",
    "source": "ref"
  }
}
