{
  "type": "Feature",
  "id": "VIDTUNCO:CO:USGS",
  "geometry": {
    "type": "Point",
    "coordinates": [
      -105.791539721414,
      39.622863653026
    ]
  },
  "properties": {
    "name": "Vidler Tunnel",
    "source": "ref",
    "begindate": "10/1/1970",
    "countyname": "Summit",
    "enddate": "2100-01-01T08:00:00Z",
    "active": true,
    "huc": 140100020202,
    "winter_start_month": 11,
    "winter_end_month": 3,
    "nwccname": "Vidler Tunnel",
    "elevation": "11700",
    "basinarea": null,
    "awdb_id": "VIDTUNCO",
    "usgs_id": "VIDTUNCO",
    "usgsname": null,
    "forecastpoint": false,
    "bagis_aoiname": null,
    "aoi_exist": null
  }
}
